AUTHORS
LICENSE.rst
MANIFEST.in
README.rst
setup.py
pytoolbox_bin/__init__.py
pytoolbox_bin/common.py
pytoolbox_bin.egg-info/PKG-INFO
pytoolbox_bin.egg-info/SOURCES.txt
pytoolbox_bin.egg-info/dependency_links.txt
pytoolbox_bin.egg-info/entry_points.txt
pytoolbox_bin.egg-info/requires.txt
pytoolbox_bin.egg-info/top_level.txt
pytoolbox_bin/apiclient/__init__.py
pytoolbox_bin/apiclient/channel.py
pytoolbox_bin/apiclient/discovery.py
pytoolbox_bin/apiclient/errors.py
pytoolbox_bin/apiclient/http.py
pytoolbox_bin/apiclient/mimeparse.py
pytoolbox_bin/apiclient/model.py
pytoolbox_bin/apiclient/sample_tools.py
pytoolbox_bin/apiclient/schema.py
pytoolbox_bin/github/__init__.py
pytoolbox_bin/github/bin.py
pytoolbox_bin/smpte2022/__init__.py
pytoolbox_bin/smpte2022/bin.py
pytoolbox_bin/smpte2022/lib/__init__.py
pytoolbox_bin/smpte2022/lib/socket_gen.py
pytoolbox_bin/smpte2022/lib/twisted_gen.py
pytoolbox_bin/tespeed/__init__.py
pytoolbox_bin/tespeed/bin.py
pytoolbox_bin/tespeed/lib.py
pytoolbox_bin/youtube/__init__.py
pytoolbox_bin/youtube/bin.py
pytoolbox_bin/youtube/lib.py