Metadata-Version: 1.1
Name: pytoolbox-bin
Version: 0.3.2-beta
Summary: Personal utility scripts based on pytoolbox and other goodies.
Home-page: https://github.com/davidfischer-ch/pytoolbox_bin
Author: David Fischer
Author-email: david.fischer.ch@gmail.com
License: EUPL 1.1
Keywords: download,gdata,github,songs,youtube
Platform: UNKNOWN
Classifier: Development Status :: 2 - Pre-Alpha
Classifier: Environment :: Console
Classifier: Intended Audience :: Developers
Classifier: Intended Audience :: End Users/Desktop
Classifier: License :: OSI Approved :: European Union Public Licence 1.1 (EUPL 1.1)
Classifier: Natural Language :: English
Classifier: Operating System :: POSIX :: Linux
Classifier: Programming Language :: Python
Classifier: Programming Language :: Python :: 2
Classifier: Programming Language :: Python :: 2.6
Classifier: Programming Language :: Python :: 2.7
Classifier: Programming Language :: Python :: Implementation :: CPython
Classifier: Topic :: Multimedia :: Sound/Audio
Classifier: Topic :: Multimedia :: Video
Classifier: Topic :: Utilities
